arbitro_muxes/probador_arbitro.v
module probador_arbitro(output reg [5:0] VC0, VC1,
                output reg clk, reset_L, pop_delay_VCO,
                input [5:0] D0, D1);

	initial begin
	$dumpfile("arbitro.vcd");
	$dumpvars;

    reset_L <= 0;
    pop_delay_VCO <= 0;
	@(posedge clk);
	@(posedge clk);
    reset_L <= 1;
    VC0 <= 6'b110100;
    VC1 <= 6'b110110;
    @(posedge clk);

    pop_delay_VCO <= 1;
    VC0 <= 6'b100101;
    VC1 <= 6'b101100;

    @(posedge clk);
    pop_delay_VCO <= 0;
    VC0 <= 6'b110100;
    VC1 <= 6'b110100;

    @(posedge clk);
    pop_delay_VCO <= 1;
    VC0 <= 6'b110110;
    VC1 <= 6'b110101;

    @(posedge clk);
    pop_delay_VCO <= 0;
    VC0 <= 6'b110110;
    VC1 <= 6'b110100;

    @(posedge clk);
    pop_delay_VCO <= 1;
    VC0 <= 6'b111101;
    VC1 <= 6'b010110;
    @(posedge clk);
    @(posedge clk);



	$finish;
	end
	initial clk <= 1;
	always #1 clk <= ~clk;
endmodule

arbitro_muxes/arbitro_demux.v
module arbitro_demux(input [5:0] mux_arbitro_1,
                    input reset_L,
                    output reg [5:0] D0, D1);

    always@(*) begin
        if(~reset_L) begin
            D0 = 0;
            D1 = 0;
        end
        else begin
            case (mux_arbitro_1[4])
                0: D0 = mux_arbitro_1;
                1: D1 = mux_arbitro_1;
            endcase
        end
    end

endmodule

arbitro_muxes/arbitro_mux.v
module arbitro_mux(input reset_L, clk,
                    input [5:0] VC0,
                    input [5:0] VC1,
                    input pop_delay_VCO,
                    output reg [5:0] mux_arbitro_1);

    always@(posedge clk) begin
       if(~reset_L) begin
           mux_arbitro_1 <= 0;
       end
       else begin
            case (pop_delay_VCO)
                0: mux_arbitro_1 <= VC1;
                1: mux_arbitro_1 <= VC0;
            endcase
       end 
    end


endmodule

arbitro_muxes/arbitro_enrutamiento.v
`include "arbitro_mux.v"
`include "arbitro_demux.v"


module arbitro_enrutamiento(input [5:0]VC0, VC1,
                            input clk, reset_L, pop_delay_VCO,
                            output [5:0] D0, D1);

    wire [5:0] mux_arbitro_1;

    arbitro_mux u_arbitro_muxes(
        .reset_L       ( reset_L       ),
        .clk           ( clk           ),
        .VC0           ( VC0 [5:0]          ),
        .VC1           ( VC1 [5:0]          ),
        .pop_delay_VCO ( pop_delay_VCO ),
        .mux_arbitro_1 ( mux_arbitro_1 [5:0] )
    );


    arbitro_demux u_arbitro_demux(
        .mux_arbitro_1 ( mux_arbitro_1[5:0] ),
        .reset_L       ( reset_L       ),
        .D0            ( D0           [5:0] ),
        .D1            ( D1           [5:0] )
    );


endmodule

arbitro_muxes/banco_pruebas.v
`include "arbitro_enrutamiento.v"
`include "probador_arbitro.v"

module bancopruebas();

    wire [5:0] VC0, VC1;
    wire [5:0] D0, D1;

    arbitro_enrutamiento u_arbitro_enrutamiento(
        .VC0           ( VC0 [5:0]          ),
        .VC1           ( VC1 [5:0]          ),
        .clk           ( clk           ),
        .reset_L       ( reset_L       ),
        .pop_delay_VCO ( pop_delay_VCO ),
        .D0            ( D0  [5:0]          ),
        .D1            ( D1  [5:0]          )
    );

    probador_arbitro u_probador(
        .VC0     ( VC0 [5:0]    ),
        .VC1     ( VC1 [5:0]    ),
        .clk     ( clk     ),
        .reset_L ( reset_L ),
        .D0      ( D0  [5:0]    ),
        .D1      ( D1  [5:0]    ),
        .pop_delay_VCO (pop_delay_VCO)
    );


endmodule

arbitro_muxes/arbitro.vcd
$date
	Tue Nov  3 15:11:48 2020
$end
$version
	Icarus Verilog
$end
$timescale
	1s
$end
$scope module bancopruebas $end
$var wire 1 ! reset_L $end
$var wire 1 " pop_delay_VCO $end
$var wire 1 # clk $end
$var wire 6 $ VC1 [5:0] $end
$var wire 6 % VC0 [5:0] $end
$var wire 6 & D1 [5:0] $end
$var wire 6 ' D0 [5:0] $end
$scope module u_arbitro_enrutamiento $end
$var wire 1 ! reset_L $end
$var wire 1 " pop_delay_VCO $end
$var wire 6 ( mux_arbitro_1 [5:0] $end
$var wire 1 # clk $end
$var wire 6 ) VC1 [5:0] $end
$var wire 6 * VC0 [5:0] $end
$var wire 6 + D1 [5:0] $end
$var wire 6 , D0 [5:0] $end
$scope module u_arbitro_demux $end
$var wire 1 ! reset_L $end
$var wire 6 - mux_arbitro_1 [5:0] $end
$var reg 6 . D0 [5:0] $end
$var reg 6 / D1 [5:0] $end
$upscope $end
$scope module u_arbitro_muxes $end
$var wire 1 ! reset_L $end
$var wire 1 " pop_delay_VCO $end
$var wire 1 # clk $end
$var wire 6 0 VC1 [5:0] $end
$var wire 6 1 VC0 [5:0] $end
$var reg 6 2 mux_arbitro_1 [5:0] $end
$upscope $end
$upscope $end
$scope module u_probador $end
$var wire 6 3 D0 [5:0] $end
$var wire 6 4 D1 [5:0] $end
$var reg 6 5 VC0 [5:0] $end
$var reg 6 6 VC1 [5:0] $end
$var reg 1 # clk $end
$var reg 1 " pop_delay_VCO $end
$var reg 1 ! reset_L $end
$upscope $end
$upscope $end
$enddefinitions $end
#0
$dumpvars
bx 6
bx 5
b0 4
b0 3
b0 2
bx 1
bx 0
b0 /
b0 .
b0 -
b0 ,
b0 +
bx *
bx )
b0 (
b0 '
b0 &
bx %
bx $
1#
0"
0!
$end
#1
0#
#2
b110110 $
b110110 )
b110110 0
b110110 6
b110100 %
b110100 *
b110100 1
b110100 5
1!
1#
#3
0#
#4
b110110 &
b110110 +
b110110 /
b110110 4
b110110 (
b110110 -
b110110 2
b101100 $
b101100 )
b101100 0
b101100 6
b100101 %
b100101 *
b100101 1
b100101 5
1"
1#
#5
0#
#6
b100101 '
b100101 ,
b100101 .
b100101 3
b110100 $
b110100 )
b110100 0
b110100 6
b110100 %
b110100 *
b110100 1
b110100 5
0"
b100101 (
b100101 -
b100101 2
1#
#7
0#
#8
b110100 &
b110100 +
b110100 /
b110100 4
b110100 (
b110100 -
b110100 2
b110101 $
b110101 )
b110101 0
b110101 6
b110110 %
b110110 *
b110110 1
b110110 5
1"
1#
#9
0#
#10
b110110 &
b110110 +
b110110 /
b110110 4
b110100 $
b110100 )
b110100 0
b110100 6
0"
b110110 (
b110110 -
b110110 2
1#
#11
0#
#12
b110100 &
b110100 +
b110100 /
b110100 4
b110100 (
b110100 -
b110100 2
b10110 $
b10110 )
b10110 0
b10110 6
b111101 %
b111101 *
b111101 1
b111101 5
1"
1#
#13
0#
#14
b111101 &
b111101 +
b111101 /
b111101 4
b111101 (
b111101 -
b111101 2
1#
